airsim/__init__.py
airsim/client.py
airsim/pfm.py
airsim/types.py
airsim/utils.py
airsim-1.3.0.dist-info/LICENSE
airsim-1.3.0.dist-info/METADATA
airsim-1.3.0.dist-info/WHEEL
airsim-1.3.0.dist-info/top_level.txt
airsim-1.3.0.dist-info/RECORD
