Metadata-Version: 2.1
Name: airsim
Version: 1.3.0
Summary: Open source simulator based on Unreal Engine for autonomous vehicles from Microsoft AI & Research
Home-page: https://github.com/microsoft/airsim
Author: Shital Shah
Author-email: shitals@microsoft.com
License: MIT
Platform: UNKNOWN
Classifier: Programming Language :: Python :: 3
Classifier: License :: OSI Approved :: MIT License
Classifier: Operating System :: OS Independent
Requires-Dist: msgpack-rpc-python
Requires-Dist: numpy
Requires-Dist: opencv-contrib-python
